ai_commit_generator/__init__.py
ai_commit_generator/cli.py
ai_commit_generator/commit_message_generator.py
ai_commit_generator/language_model_factory.py
ai_commit_generator/main.py
ai_commit_generator/schemas.py
ai_commit_generator-0.0.1.dist-info/METADATA
ai_commit_generator-0.0.1.dist-info/WHEEL
ai_commit_generator-0.0.1.dist-info/entry_points.txt
ai_commit_generator-0.0.1.dist-info/top_level.txt
ai_commit_generator-0.0.1.dist-info/RECORD
